orca_retargeter/retargeter.py
orca_retargeter/utils/__init__.py
orca_retargeter/utils/load_utils.py
orca_retargeter/utils/retarget_utils.py
orca_retargeter/utils/yaml_utils.py
orca_retargeter-0.1.0.dist-info/LICENSE
orca_retargeter-0.1.0.dist-info/METADATA
orca_retargeter-0.1.0.dist-info/WHEEL
orca_retargeter-0.1.0.dist-info/RECORD
